pinax/__init__.py
pinax/likes/__init__.py
pinax/likes/admin.py
pinax/likes/apps.py
pinax/likes/auth_backends.py
pinax/likes/conf.py
pinax/likes/models.py
pinax/likes/signals.py
pinax/likes/urls.py
pinax/likes/utils.py
pinax/likes/views.py
pinax/likes/migrations/0001_initial.py
pinax/likes/migrations/0002_auto_20190906_2058.py
pinax/likes/migrations/__init__.py
pinax/likes/templatetags/__init__.py
pinax/likes/templatetags/pinax_likes_tags.py
pinax/likes/tests/__init__.py
pinax/likes/tests/models.py
pinax/likes/tests/test_models.py
pinax/likes/tests/test_tags.py
pinax/likes/tests/test_utils.py
pinax/likes/tests/test_views.py
pinax/likes/tests/urls.py
pinax_likes-4.0.0.dist-info/AUTHORS
pinax_likes-4.0.0.dist-info/LICENSE
pinax_likes-4.0.0.dist-info/METADATA
pinax_likes-4.0.0.dist-info/WHEEL
pinax_likes-4.0.0.dist-info/top_level.txt
pinax_likes-4.0.0.dist-info/RECORD
